doq/__init__.py
doq/__main__.py
doq/main.py
doq/parser.py
doq/validator.py
doq/version
doq/version.py
doq/providers/__init__.py
doq/providers/claude.py
doq/providers/deepseek.py
doq/providers/openai.py
doque-0.1.1.data/scripts/doq_unix
doque-0.1.1.dist-info/licenses/LICENSE
tests/__init__.py
tests/test_config_validation.py
tests/test_cost_control.py
tests/test_file_inclusion_markers.py
tests/test_main.py
tests/test_parser.py
tests/test_parser_basic.py
tests/test_parser_directories.py
tests/test_parser_files.py
tests/test_parser_urls.py
tests/test_provider_validation.py
tests/test_providers.py
doque-0.1.1.dist-info/METADATA
doque-0.1.1.dist-info/WHEEL
doque-0.1.1.dist-info/entry_points.txt
doque-0.1.1.dist-info/top_level.txt
doque-0.1.1.dist-info/RECORD
