Metadata-Version: 2.4
Name: doque
Version: 0.1.1
Summary: A command-line interface for various LLM providers (Claude, ChatGPT, DeepSeek)
Home-page: https://github.com/ko10ok/do
Author: Yuriy Sagitov
Author-email: home_r@mail.ru
License: Apache-2.0
Keywords: llm ai cli claude chatgpt deepseek anthropic openai
Classifier: Development Status :: 4 - Beta
Classifier: Intended Audience :: Developers
Classifier: License :: OSI Approved :: Apache Software License
Classifier: Programming Language :: Python :: 3
Classifier: Programming Language :: Python :: 3.9
Classifier: Programming Language :: Python :: 3.10
Classifier: Programming Language :: Python :: 3.11
Classifier: Programming Language :: Python :: 3.12
Requires-Python: >=3.9
License-File: LICENSE
Dynamic: author
Dynamic: author-email
Dynamic: classifier
Dynamic: description
Dynamic: description-content-type
Dynamic: home-page
Dynamic: keywords
Dynamic: license
Dynamic: license-file
Dynamic: requires-python
Dynamic: summary
